lexmachina/__about__.py
lexmachina/__init__.py
lexmachina/api_client.py
lexmachina/api_response.py
lexmachina/configuration.py
lexmachina/exceptions.py
lexmachina/rest.py
lexmachina/api/__init__.py
lexmachina/api/alerts_api.py
lexmachina/api/attorneys_api.py
lexmachina/api/authorization_api.py
lexmachina/api/bankruptcy_cases_api.py
lexmachina/api/case_query_api.py
lexmachina/api/dockets_api.py
lexmachina/api/entities_api.py
lexmachina/api/federal_appeals_cases_api.py
lexmachina/api/federal_district_cases_api.py
lexmachina/api/find_api.py
lexmachina/api/itc_investigations_api.py
lexmachina/api/judges_api.py
lexmachina/api/law_firms_api.py
lexmachina/api/list_api.py
lexmachina/api/parties_api.py
lexmachina/api/patents_api.py
lexmachina/api/ptab_trials_api.py
lexmachina/api/search_api.py
lexmachina/api/state_cases_api.py
lexmachina/api/status_api.py
lexmachina/docs/AdministrativeLawJudge.md
lexmachina/docs/AdministrativePatentJudge.md
lexmachina/docs/AdministrativePatentJudgeDetail.md
lexmachina/docs/Alert.md
lexmachina/docs/AlertItem.md
lexmachina/docs/AlertRunData.md
lexmachina/docs/AlertRunResult.md
lexmachina/docs/AlertsApi.md
lexmachina/docs/Amount.md
lexmachina/docs/Amountperdefendant.md
lexmachina/docs/AppealsAttorneyFilter.md
lexmachina/docs/AppealsCase.md
lexmachina/docs/AppealsCaseData.md
lexmachina/docs/AppealsCaseDates.md
lexmachina/docs/AppealsCaseDatesFilter.md
lexmachina/docs/AppealsCaseQuery.md
lexmachina/docs/AppealsCaseQueryResult.md
lexmachina/docs/AppealsCaseReference.md
lexmachina/docs/AppealsLawFirmFilter.md
lexmachina/docs/AppealsPartyFilter.md
lexmachina/docs/AppellateDecisionFilter.md
lexmachina/docs/Attorney.md
lexmachina/docs/AttorneyData.md
lexmachina/docs/AttorneyFilter.md
lexmachina/docs/AttorneyReference.md
lexmachina/docs/AttorneyResult.md
lexmachina/docs/AttorneySearchResults.md
lexmachina/docs/AttorneysApi.md
lexmachina/docs/AuthorizationApi.md
lexmachina/docs/BankruptcyCaseData.md
lexmachina/docs/BankruptcyCaseDates.md
lexmachina_client-2.0.0.20250708.dist-info/METADATA
lexmachina_client-2.0.0.20250708.dist-info/WHEEL
lexmachina_client-2.0.0.20250708.dist-info/licenses/LICENSE
lexmachina_client-2.0.0.20250708.dist-info/RECORD
