Metadata-Version: 2.4
Name: lexmachina-client
Version: 2.0.0.20250708
Summary: LexMachina API python SDK
Project-URL: Documentation, https://github.com/LexMachinaInc/python-lexmachina-sync-api-client
Project-URL: Issues, https://github.com/LexMachinaInc/python-lexmachina-sync-api-client/issues
Project-URL: Source, https://github.com/LexMachinaInc/python-lexmachina-sync-api-client
Project-URL: Changelog, https://github.com/LexMachinaInc/python-lexmachina-sync-api-client/blob/main/CHANGELOG.md
Author-email: LexMachina <support@lexmachina.com>
License-Expression: Apache-2.0
License-File: LICENSE
Classifier: Development Status :: 4 - Beta
Classifier: Intended Audience :: Developers
Classifier: Intended Audience :: Legal Industry
Classifier: License :: OSI Approved :: Apache Software License
Classifier: Operating System :: OS Independent
Classifier: Programming Language :: Python
Classifier: Programming Language :: Python :: 3.8
Classifier: Programming Language :: Python :: 3.9
Classifier: Programming Language :: Python :: 3.10
Classifier: Programming Language :: Python :: 3.11
Classifier: Programming Language :: Python :: 3.12
Classifier: Programming Language :: Python :: Implementation :: CPython
Classifier: Programming Language :: Python :: Implementation :: PyPy
Requires-Python: >=3.8
Requires-Dist: aiohttp>=3.8.3
Requires-Dist: pydantic>=2
Requires-Dist: python-dateutil>=2.8.2
Requires-Dist: requests>=2.28.1
Requires-Dist: typing-extensions>=4.7.1
Requires-Dist: urllib3<3.0.0,>=2.1.0
Provides-Extra: dev
Requires-Dist: ipython>=8.14.0; extra == 'dev'
Requires-Dist: jupyterlab>=4.0.0; extra == 'dev'
Provides-Extra: tests
Requires-Dist: pytest-asyncio>=0.21.0; extra == 'tests'
Requires-Dist: pytest>=7.2.1; extra == 'tests'
